release_info/__init__.py
release_info/apps.py
release_info/urls.py
release_info/views.py
release_info/templates/release_info/release.html
django_release_info-0.0.6.dist-info/LICENSE
django_release_info-0.0.6.dist-info/METADATA
django_release_info-0.0.6.dist-info/WHEEL
django_release_info-0.0.6.dist-info/top_level.txt
django_release_info-0.0.6.dist-info/RECORD
